{
    "tcs_3F_mite_325_SE_331-01": {
        "x": 126,
        "y": 94,
        "value": 81
    },
    "tcs_3F_mite_325_NW_331-02": {
        "x": 105,
        "y": 57,
        "value": 90
    },
    "tcs_3F_mite_326_NW_331-04": {
        "x": 148,
        "y": 60,
        "value": 97
    },
    "tcs_3F_mite_326_SE_331-03": {
        "x": 168,
        "y": 90,
        "value": 62
    },
    "tcs_3F_mite_327_SW_331-05": {
        "x": 190,
        "y": 88,
        "value": 50
    },
    "tcs_3F_mite_327_NE_331-06": {
        "x": 212,
        "y": 60,
        "value": 86
    },
    "tcs_3F_mite_324_SE_332-08": {
        "x": 158,
        "y": 159,
        "value": 80
    },
    "tcs_3F_mite_324_SW_332-09": {
        "x": 117,
        "y": 151,
        "value": 80
    },
    "tcs_3F_mite_323_NE_332-10": {
        "x": 154,
        "y": 170,
        "value": 82
    },
    "tcs_3F_mite_323_SW_332-11": {
        "x": 115,
        "y": 188,
        "value": 89
    },
    "tcs_3F_mite_322_SE_335-09": {
        "x": 157,
        "y": 235,
        "value": 51
    },
    "tcs_3F_mite_322_SW_332-12": {
        "x": 114,
        "y": 227,
        "value": 84
    },
    "tcs_3F_mite_321_SW_332-14": {
        "x": 116,
        "y": 264,
        "value": 76
    },
    "tcs_3F_room_321_NE_332-13": {
        "x": 155,
        "y": 246,
        "value": 51
    },
    "tcs_3F_mite_320_SW_332-16": {
        "x": 123,
        "y": 302,
        "value": 72
    },
    "tcs_3F_mite_320_NE_332-15": {
        "x": 165,
        "y": 287,
        "value": 99
    },
    "tcs_3F_mite_331A_S_332-20": {
        "x": 211,
        "y": 262,
        "value": 94
    },
    "tcs_3F_mite_331_SE_332-18": {
        "x": 223,
        "y": 226,
        "value": 53
    },
    "tcs_3F_mite_331_N__332-19": {
        "x": 212,
        "y": 202,
        "value": 68
    },
    "tcs_3F_mite_332_NE_332-17": {
        "x": 223,
        "y": 143,
        "value": 80
    },
    "tcs_3F_mite_330_NE_332-21": {
        "x": 214,
        "y": 291,
        "value": 52
    },
    "tcs_3F_mite_340_NW_331-08": {
        "x": 356,
        "y": 61,
        "value": 83
    },
    "tcs_3F_mite_340_SE_331-07": {
        "x": 370,
        "y": 90,
        "value": 98
    },
    "tcs_3F_mite_341_N_331-10": {
        "x": 406,
        "y": 60,
        "value": 80
    },
    "tcs_3F_mite_341_SW_331-09": {
        "x": 392,
        "y": 89,
        "value": 86
    },
    "tcs_3F_mite_342_N_331-12": {
        "x": 438,
        "y": 67,
        "value": 94
    },
    "tcs_3F_mite_342_SE_331-11": {
        "x": 456,
        "y": 86,
        "value": 91
    },
    "tcs_3F_mite_343_SW_331-13": {
        "x": 473,
        "y": 90,
        "value": 62
    },
    "tcs_3F_mite_343_N_331-14": {
        "x": 486,
        "y": 62,
        "value": 85
    },
    "tcs_3F_mite_344_SW_331-15": {
        "x": 513,
        "y": 88,
        "value": 68
    },
    "tcs_3F_mite_345_NW_331-17": {
        "x": 550,
        "y": 61,
        "value": 99
    },
    "tcs_3F_mite_345_SE_331-16": {
        "x": 571,
        "y": 92,
        "value": 79
    },
    "tcs_3F_mite_346_SW_331-18": {
        "x": 593,
        "y": 89,
        "value": 66
    },
    "tcs_3F_mite_346_E_331-19": {
        "x": 613,
        "y": 69,
        "value": 64
    },
    "tcs_3F_mite_347_N_331-21": {
        "x": 638,
        "y": 60,
        "value": 67
    },
    "tcs_3F_mite_347_SE_331-20": {
        "x": 651,
        "y": 91,
        "value": 50
    },
    "tcs_3F_mite_348_SW_331-22": {
        "x": 673,
        "y": 88,
        "value": 55
    },
    "tcs_3F_mite_348_NE_331-23": {
        "x": 692,
        "y": 74,
        "value": 52
    },
    "tcs_3F_mite_349_N_334-24": {
        "x": 702,
        "y": 111,
        "value": 97
    },
    "tcs_3F_mite_349_E_332-01": {
        "x": 720,
        "y": 141,
        "value": 76
    },
    "tcs_3F_mite_363_N_332-03": {
        "x": 745,
        "y": 122,
        "value": 85
    },
    "tcs_3F_mite_363_S_332-02": {
        "x": 751,
        "y": 165,
        "value": 95
    },
    "tcs_3F_mite_362_N_332-05": {
        "x": 786,
        "y": 118,
        "value": 62
    },
    "tcs_3F_mite_362_SW_332-04": {
        "x": 776,
        "y": 160,
        "value": 85
    },
    "tcs_3F_mite_361_N_332-07": {
        "x": 825,
        "y": 120,
        "value": 80
    },
    "tcs_3F_mite_361_SW_332-06": {
        "x": 812,
        "y": 159,
        "value": 77
    },
    "tcs_3F_mite_317_N_335-09": {
        "x": 237,
        "y": 398,
        "value": 87
    },
    "tcs_3F_mite_317_E_335-10": {
        "x": 251,
        "y": 424,
        "value": 78
    },
    "tcs_3F_mite_316_NE_335-11": {
        "x": 289,
        "y": 400,
        "value": 58
    },
    "tcs_3F_mite_316_W_335-12": {
        "x": 271,
        "y": 423,
        "value": 87
    },
    "tcs_3F_mite_315_NE_335-13": {
        "x": 330,
        "y": 403,
        "value": 69
    },
    "tcs_3F_mite_315_cen_335-14": {
        "x": 318,
        "y": 420,
        "value": 51
    },
    "tcs_3F_mite_314_NW_335-15": {
        "x": 353,
        "y": 405,
        "value": 97
    },
    "tcs_3F_mite_314_SE_335-16": {
        "x": 372,
        "y": 429,
        "value": 58
    },
    "tcs_3F_mite_313_NW_335-17": {
        "x": 393,
        "y": 401,
        "value": 86
    },
    "tcs_3F_mite_313_E_335-18": {
        "x": 413,
        "y": 425,
        "value": 52
    },
    "tcs_3F_mite_312_W_335-20": {
        "x": 436,
        "y": 420,
        "value": 95
    },
    "tcs_3F_mite_312_NE_335-19": {
        "x": 448,
        "y": 405,
        "value": 85
    },
    "tcs_3F_mite_311_NW_335-21": {
        "x": 472,
        "y": 403,
        "value": 99
    },
    "tcs_3F_mite_311_SE_335-22": {
        "x": 485,
        "y": 428,
        "value": 87
    },
    "tcs_3F_mite_310_NW__336-01": {
        "x": 522,
        "y": 430,
        "value": 93
    },
    "tcs_3F_mite_310_NE_335-23": {
        "x": 568,
        "y": 413,
        "value": 71
    },
    "tcs_3F_mite_310_S_335-24": {
        "x": 566,
        "y": 430,
        "value": 53
    },
    "tcs_3F_mite_358_NW_334-07": {
        "x": 348,
        "y": 155,
        "value": 72
    },
    "tcs_3F_mite_358_cen_335-07": {
        "x": 355,
        "y": 176,
        "value": 64
    },
    "tcs_3F_mite_358_SW_334-05": {
        "x": 354,
        "y": 235,
        "value": 63
    },
    "tcs_3F_mite_358_NE_334-02": {
        "x": 433,
        "y": 149,
        "value": 82
    },
    "tcs_3F_mite_358_E_334-03": {
        "x": 422,
        "y": 179,
        "value": 86
    },
    "tcs_3F_mite_358_SE_334-04": {
        "x": 422,
        "y": 234,
        "value": 71
    },
    "tcs_3F_mite_353_NE_334-08": {
        "x": 500,
        "y": 137,
        "value": 57
    },
    "tcs_3F_mite_353_cen_334-09": {
        "x": 472,
        "y": 166,
        "value": 84
    },
    "tcs_3F_mite_355_NE_334-10": {
        "x": 500,
        "y": 196,
        "value": 66
    },
    "tcs_3F_mite_355_W_334-11": {
        "x": 463,
        "y": 216,
        "value": 51
    },
    "tcs_3F_mite_357_NE_334-12": {
        "x": 494,
        "y": 245,
        "value": 92
    },
    "tcs_3F_mite_357_W_334-13": {
        "x": 463,
        "y": 259,
        "value": 54
    },
    "tcs_3F_mite_350_NW_334-14": {
        "x": 548,
        "y": 137,
        "value": 73
    },
    "tcs_3F_mite_350_N_334-15": {
        "x": 587,
        "y": 149,
        "value": 77
    },
    "tcs_3F_mite_350_NE_334-16": {
        "x": 632,
        "y": 150,
        "value": 60
    },
    "tcs_3F_mite_350_SE_334-18": {
        "x": 632,
        "y": 236,
        "value": 59
    },
    "tcs_3F_mite_350_E_334-17": {
        "x": 632,
        "y": 194,
        "value": 75
    },
    "tcs_3F_mite_350_W__334-24": {
        "x": 549,
        "y": 195,
        "value": 95
    },
    "tcs_3F_mite_350_SW_334-23": {
        "x": 549,
        "y": 236,
        "value": 86
    },
    "tcs_3F_mite_350_ent_334-20": {
        "x": 549,
        "y": 276,
        "value": 61
    },
    "tcs_3F_mite_350_ent_334-19": {
        "x": 572,
        "y": 264,
        "value": 79
    },
    "tcs_3F_mite_350_S_334-21": {
        "x": 586,
        "y": 235,
        "value": 74
    },
    "tcs_3F_mite_350_cen_334-22": {
        "x": 587,
        "y": 195,
        "value": 82
    },
    "tcs_3F_mite_C303_W_332-23": {
        "x": 259,
        "y": 165,
        "value": 93
    },
    "tcs_3F_mite_C303_E_332-24": {
        "x": 312,
        "y": 163,
        "value": 67
    },
    "tcs_3F_mite_hallwayC_W_334-01": {
        "x": 359,
        "y": 118,
        "value": 82
    },
    "tcs_3F_mite_307_W_332-22": {
        "x": 250,
        "y": 371,
        "value": 57
    },
    "tcs_3F_mite_300_E_336-02": {
        "x": 626,
        "y": 278,
        "value": 70
    },
    "tcs_3F_mite_360_NE_334-06": {
        "x": 796,
        "y": 192,
        "value": 95
    },
    "tcs_3F_mite_360_SE_334-07": {
        "x": 817,
        "y": 250,
        "value": 80
    },
    "tcs_3F_mite_360_N_334-05": {
        "x": 777,
        "y": 249,
        "value": 90
    },
    "tcs_3F_mite_360_NW_334-04": {
        "x": 739,
        "y": 250,
        "value": 56
    },
    "tcs_3F_mite_360_SW_334-03": {
        "x": 722,
        "y": 281,
        "value": 79
    },
    "tcs_3F_mite_hallwayC_E_335-01": {
        "x": 669,
        "y": 119,
        "value": 73
    },
    "tcs_3F_mite_364_N_335-08": {
        "x": 744,
        "y": 195,
        "value": 60
    },
    "tcs_3F_mite_364_S_335-02": {
        "x": 694,
        "y": 240,
        "value": 68
    },
    "tcs_3F_mite_hallwayC_center_336-06": {
        "x": 519,
        "y": 118,
        "value": 57
    },
    "tcs_3F_mite_300_L_S_336-05": {
        "x": 327,
        "y": 350,
        "value": 65
    },
    "tcs_3F_mite_307_E_336-04": {
        "x": 491,
        "y": 371,
        "value": 53
    },
    "tcs_3F_mite_300_R_center_336-03": {
        "x": 535,
        "y": 324,
        "value": 100
    },
    "tcs_3F_mite_hallwayL_center_": {
        "x": 175,
        "y": 119,
        "value": 86
    },
    "tcs_3F_mite_C303_N_336-07": {
        "x": 242,
        "y": 85,
        "value": 51
    },
    "tcs_3F_mite_C303_S_336-09": {
        "x": 250,
        "y": 225,
        "value": 61
    }
}